{
 "id": "b1cf6a10-0d6e-4612-92a3-3aa677796484",
 "type": "paragraph",
 "childs": [
  {
   "id": "091af755-9931-459f-8c4b-ef385f2e8f79",
   "type": "sentence",
   "childs": [
    {
     "id": "6597a301-af5c-4919-98d7-4068a4a0dec7",
     "type": "subSentence",
     "childs": [
      {
       "id": "e4b6bda8-4788-4259-9f61-3de0fbd97f90",
       "type": "word",
       "value": "Найбільш",
       "textRange": [
        1544,
        1552
       ],
       "concept": "SYNTAX"
      },
      {
       "id": "149d11c5-7bfb-47fe-9ddd-e56715c1f8a2",
       "type": "whitespace",
       "value": " ",
       "textRange": [
        1552,
        1553
       ],
       "concept": "SYNTAX"
      },
      {
       "id": "341358d0-8dd0-478f-80b2-1887b765234c",
       "type": "word",
       "value": "активні",
       "textRange": [
        1553,
        1560
       ],
       "concept": "SYNTAX"
      },
      {
       "id": "59ee340e-774a-4803-941a-2377941db60d",
       "type": "whitespace",
       "value": " ",
       "textRange": [
        1560,
        1561
       ],
       "concept": "SYNTAX"
      },
      {
       "id": "c418b271-48e5-46b2-a47b-b71b42fa2079",
       "type": "word",
       "value": "збудники",
       "textRange": [
        1561,
        1569
       ],
       "concept": "SYNTAX"
      },
      {
       "id": "c0b9c6f3-80fe-46ba-984f-df93cf310bac",
       "type": "whitespace",
       "value": " ",
       "textRange": [
        1569,
        1570
       ],
       "concept": "SYNTAX"
      },
      {
       "id": "58bec11d-011b-400e-8cd1-88e167c4114f",
       "type": "word",
       "value": "інфекцій",
       "textRange": [
        1570,
        1578
       ],
       "concept": "SYNTAX"
      },
      {
       "id": "0efd092c-c78c-4268-b649-8b0a6014e3f9",
       "type": "whitespace",
       "value": " ",
       "textRange": [
        1578,
        1579
       ],
       "concept": "SYNTAX"
      },
      {
       "id": "c17b71db-1853-4f4b-8ba7-9969fdf835dd",
       "type": "word",
       "value": "сечових",
       "textRange": [
        1579,
        1586
       ],
       "concept": "SYNTAX"
      },
      {
       "id": "7fda8a83-baa3-40e2-aa5d-5671cc15e54f",
       "type": "whitespace",
       "value": " ",
       "textRange": [
        1586,
        1587
       ],
       "concept": "SYNTAX"
      },
      {
       "id": "a8695be7-61bd-4d93-bfb9-7e970d10638d",
       "type": "word",
       "value": "шляхів",
       "textRange": [
        1587,
        1593
       ],
       "concept": "SYNTAX"
      },
      {
       "id": "5d905a06-50cd-4ea3-9e5b-b93d43e5afc9",
       "type": "whitespace",
       "value": " ",
       "textRange": [
        1593,
        1594
       ],
       "concept": "SYNTAX"
      },
      {
       "id": "989c5dc5-6e69-4bfc-b3d3-36d89fc99f9b",
       "type": "whitespace",
       "value": "—",
       "textRange": [
        1594,
        1595
       ],
       "concept": "SYNTAX"
      },
      {
       "id": "b2a18dcc-05e9-4a60-9ae3-5c7427dafb85",
       "type": "whitespace",
       "value": " ",
       "textRange": [
        1595,
        1596
       ],
       "concept": "SYNTAX"
      },
      {
       "id": "5600666b-b308-4542-b932-b6e348b72a87",
       "type": "word",
       "value": "кишкова",
       "textRange": [
        1596,
        1603
       ],
       "concept": "SYNTAX"
      },
      {
       "id": "72dc179a-1d1e-4a12-b2c4-89b3731c073e",
       "type": "whitespace",
       "value": " ",
       "textRange": [
        1603,
        1604
       ],
       "concept": "SYNTAX"
      },
      {
       "id": "7b2ca6f6-41dd-4e78-8cac-0a332d4a63f0",
       "type": "word",
       "value": "паличка",
       "textRange": [
        1604,
        1611
       ],
       "concept": "SYNTAX"
      }
     ],
     "value": "Найбільш активні збудники інфекцій сечових шляхів — кишкова паличка",
     "concept": "SYNTAX"
    },
    {
     "id": "81549167-f68a-453a-9ab4-83524e611050",
     "type": "punctuation",
     "value": ",",
     "textRange": [
      1611,
      1612
     ],
     "concept": "SYNTAX"
    },
    {
     "id": "c5a2cc08-217b-46de-b1aa-1579de70c554",
     "type": "subSentence",
     "childs": [
      {
       "id": "bf0d803e-2e64-48dd-9ee9-8fae95f1df32",
       "type": "whitespace",
       "value": " ",
       "textRange": [
        1612,
        1613
       ],
       "concept": "SYNTAX"
      },
      {
       "id": "202d54ba-540b-4c9c-9084-7ca5fee6d9c2",
       "type": "word",
       "value": "або",
       "textRange": [
        1613,
        1616
       ],
       "concept": "SYNTAX"
      },
      {
       "id": "c527c503-a338-487e-9463-551efa6c7d05",
       "type": "whitespace",
       "value": " ",
       "textRange": [
        1616,
        1617
       ],
       "concept": "SYNTAX"
      },
      {
       "id": "db633995-0821-45de-bdef-236b4a5ab26f",
       "type": "word",
       "value": "ентерокок",
       "textRange": [
        1617,
        1626
       ],
       "concept": "SYNTAX"
      }
     ],
     "value": " або ентерокок",
     "concept": "SYNTAX"
    },
    {
     "id": "c52b962d-c836-437b-9544-291acf1262bb",
     "type": "punctuation",
     "value": ",",
     "textRange": [
      1626,
      1627
     ],
     "concept": "SYNTAX"
    },
    {
     "id": "35922457-0b2e-494e-b7ee-9468a39ef4c5",
     "type": "subSentence",
     "childs": [
      {
       "id": "b8b36597-e580-44e8-87ca-dcd41ecb6cd4",
       "type": "whitespace",
       "value": " ",
       "textRange": [
        1627,
        1628
       ],
       "concept": "SYNTAX"
      },
      {
       "id": "2066f537-5fb7-4e01-bd1b-81cacf32c555",
       "type": "word",
       "value": "іноді",
       "textRange": [
        1628,
        1633
       ],
       "concept": "SYNTAX"
      },
      {
       "id": "9b7795e9-b786-4c1a-804e-e6c83687b32b",
       "type": "whitespace",
       "value": " ",
       "textRange": [
        1633,
        1634
       ],
       "concept": "SYNTAX"
      },
      {
       "id": "dc15f5b5-7788-4bc6-bbad-4d9ede671020",
       "type": "word",
       "value": "провокатором",
       "textRange": [
        1634,
        1646
       ],
       "concept": "SYNTAX"
      },
      {
       "id": "b9ea78d7-7509-4d1f-8f07-a43ea54873fc",
       "type": "whitespace",
       "value": " ",
       "textRange": [
        1646,
        1647
       ],
       "concept": "SYNTAX"
      },
      {
       "id": "b918a17f-e20e-44a9-8c3b-e0a0e2a5263c",
       "type": "word",
       "value": "запальних",
       "textRange": [
        1647,
        1656
       ],
       "concept": "SYNTAX"
      },
      {
       "id": "95b8cd80-3d79-46f2-b418-d8a581237b39",
       "type": "whitespace",
       "value": " ",
       "textRange": [
        1656,
        1657
       ],
       "concept": "SYNTAX"
      },
      {
       "id": "63e21c13-74d7-41eb-84e8-ca1dcad279d1",
       "type": "word",
       "value": "процесів",
       "textRange": [
        1657,
        1665
       ],
       "concept": "SYNTAX"
      },
      {
       "id": "fdee41e0-6e1f-4885-8637-c176f0618296",
       "type": "whitespace",
       "value": " ",
       "textRange": [
        1665,
        1666
       ],
       "concept": "SYNTAX"
      },
      {
       "id": "50130741-7715-473f-84d9-16de9253ad0c",
       "type": "word",
       "value": "стає",
       "textRange": [
        1666,
        1670
       ],
       "concept": "SYNTAX"
      },
      {
       "id": "9ea35215-ccdb-4618-a230-2745d2aaebb8",
       "type": "whitespace",
       "value": " ",
       "textRange": [
        1670,
        1671
       ],
       "concept": "SYNTAX"
      },
      {
       "id": "f785a9cc-b526-4c78-bcae-46e8e9d50dcd",
       "type": "word",
       "value": "стафілокок",
       "textRange": [
        1671,
        1681
       ],
       "concept": "SYNTAX"
      }
     ],
     "value": " іноді провокатором запальних процесів стає стафілокок",
     "concept": "SYNTAX"
    },
    {
     "id": "073f164b-34d1-42f9-a644-fb05b9b60979",
     "type": "punctuation",
     "value": ".",
     "textRange": [
      1681,
      1682
     ],
     "concept": "SYNTAX"
    }
   ],
   "value": "Найбільш активні збудники інфекцій сечових шляхів — кишкова паличка, або ентерокок, іноді провокатором запальних процесів стає стафілокок",
   "concept": "SYNTAX"
  },
  {
   "id": "796e5b95-ec5a-459d-a559-2dce75852d24",
   "type": "sentence",
   "childs": [
    {
     "id": "fbbb0757-4624-4e06-b2fc-900c0c3619f0",
     "type": "subSentence",
     "childs": [
      {
       "id": "b01504c0-16a2-48d6-bdeb-496b090ace48",
       "type": "whitespace",
       "value": " ",
       "textRange": [
        1682,
        1683
       ],
       "concept": "SYNTAX"
      },
      {
       "id": "5cf9e102-bfc3-4610-92e1-61eebe72e945",
       "type": "word",
       "value": "Спричинити",
       "textRange": [
        1683,
        1693
       ],
       "concept": "SYNTAX"
      },
      {
       "id": "d0efa132-5bbe-49ef-b495-58689bfaab71",
       "type": "whitespace",
       "value": " ",
       "textRange": [
        1693,
        1694
       ],
       "concept": "SYNTAX"
      },
      {
       "id": "ba1b32d4-7701-4136-b2fc-30a599dc82b0",
       "type": "word",
       "value": "хворобу",
       "textRange": [
        1694,
        1701
       ],
       "concept": "SYNTAX"
      },
      {
       "id": "f190eeed-e44e-4875-9b24-ac8daf7ca637",
       "type": "whitespace",
       "value": " ",
       "textRange": [
        1701,
        1702
       ],
       "concept": "SYNTAX"
      },
      {
       "id": "edb03b68-2448-4399-a400-8dfe91b5b89d",
       "type": "word",
       "value": "можуть",
       "textRange": [
        1702,
        1708
       ],
       "concept": "SYNTAX"
      },
      {
       "id": "150564d4-7697-402c-bbfb-b1ab9d7132e3",
       "type": "whitespace",
       "value": " ",
       "textRange": [
        1708,
        1709
       ],
       "concept": "SYNTAX"
      },
      {
       "id": "34de0426-09a4-4b4a-93a3-ad98518c3960",
       "type": "word",
       "value": "віруси",
       "textRange": [
        1709,
        1715
       ],
       "concept": "SYNTAX"
      }
     ],
     "value": " Спричинити хворобу можуть віруси",
     "concept": "SYNTAX"
    },
    {
     "id": "58126500-948f-4623-9d5a-5e2c6605eaf2",
     "type": "punctuation",
     "value": ",",
     "textRange": [
      1715,
      1716
     ],
     "concept": "SYNTAX"
    },
    {
     "id": "58818fc0-afa1-4922-aba5-68224ca3f213",
     "type": "subSentence",
     "childs": [
      {
       "id": "b2e10c66-1e24-4810-ad50-114fa6b0536b",
       "type": "whitespace",
       "value": " ",
       "textRange": [
        1716,
        1717
       ],
       "concept": "SYNTAX"
      },
      {
       "id": "1255c3d2-8824-4602-99b3-1b6c484a383b",
       "type": "word",
       "value": "гельмінти",
       "textRange": [
        1717,
        1726
       ],
       "concept": "SYNTAX"
      },
      {
       "id": "731fe89d-8bdf-45d6-ac2c-4459d6c56d74",
       "type": "whitespace",
       "value": " ",
       "textRange": [
        1726,
        1727
       ],
       "concept": "SYNTAX"
      },
      {
       "id": "f6816537-3b53-492e-973b-64404b2f3d6d",
       "type": "whitespace",
       "value": "(",
       "textRange": [
        1727,
        1728
       ],
       "concept": "SYNTAX"
      },
      {
       "id": "10aa1c10-d9e7-4fe3-b94b-fba7082cd79d",
       "type": "word",
       "value": "паразити",
       "textRange": [
        1728,
        1736
       ],
       "concept": "SYNTAX"
      },
      {
       "id": "af4168dd-9a32-4857-b353-21063abd0efc",
       "type": "whitespace",
       "value": ")",
       "textRange": [
        1736,
        1737
       ],
       "concept": "SYNTAX"
      },
      {
       "id": "73c312ce-918c-41d5-bd4f-ccd860c7af40",
       "type": "whitespace",
       "value": " ",
       "textRange": [
        1737,
        1738
       ],
       "concept": "SYNTAX"
      },
      {
       "id": "460fdd6e-ca4d-42f9-81df-799f577e0898",
       "type": "word",
       "value": "і",
       "textRange": [
        1738,
        1739
       ],
       "concept": "SYNTAX"
      },
      {
       "id": "649d45f5-af7f-47f9-a28a-af6b8d4ca6fd",
       "type": "whitespace",
       "value": " ",
       "textRange": [
        1739,
        1740
       ],
       "concept": "SYNTAX"
      },
      {
       "id": "100c793a-a853-485e-805c-072894b431d6",
       "type": "word",
       "value": "навіть",
       "textRange": [
        1740,
        1746
       ],
       "concept": "SYNTAX"
      },
      {
       "id": "0b3247a9-c8b7-4372-9a61-6a44aae0cdea",
       "type": "whitespace",
       "value": " ",
       "textRange": [
        1746,
        1747
       ],
       "concept": "SYNTAX"
      },
      {
       "id": "b8ab8b7b-7c19-43b7-9273-d2313ee62082",
       "type": "word",
       "value": "сечовий",
       "textRange": [
        1747,
        1754
       ],
       "concept": "SYNTAX"
      },
      {
       "id": "ded919e8-b484-4c9f-8850-3c93ad1ff038",
       "type": "whitespace",
       "value": " ",
       "textRange": [
        1754,
        1755
       ],
       "concept": "SYNTAX"
      },
      {
       "id": "383db749-0f01-49cd-a8c9-5467ab5a4a1b",
       "type": "word",
       "value": "катетер",
       "textRange": [
        1755,
        1762
       ],
       "concept": "SYNTAX"
      }
     ],
     "value": " гельмінти (паразити) і навіть сечовий катетер",
     "concept": "SYNTAX"
    },
    {
     "id": "6996b8ec-d18d-48e1-bf46-25ceb0a777d8",
     "type": "punctuation",
     "value": ",",
     "textRange": [
      1762,
      1763
     ],
     "concept": "SYNTAX"
    },
    {
     "id": "133bca58-d14f-4969-843d-307294b9a890",
     "type": "subSentence",
     "childs": [
      {
       "id": "8e6a6486-7345-4e82-a7d2-735243fcca48",
       "type": "whitespace",
       "value": " ",
       "textRange": [
        1763,
        1764
       ],
       "concept": "SYNTAX"
      },
      {
       "id": "d517e2b5-01e3-495c-9c8c-a4bbbfbfffbf",
       "type": "word",
       "value": "якщо",
       "textRange": [
        1764,
        1768
       ],
       "concept": "SYNTAX"
      },
      {
       "id": "45feb4fa-25ad-4bf9-b047-7664297b7098",
       "type": "whitespace",
       "value": " ",
       "textRange": [
        1768,
        1769
       ],
       "concept": "SYNTAX"
      },
      {
       "id": "5adae970-a104-47d7-ba14-3a7a44999c63",
       "type": "word",
       "value": "пацієнту",
       "textRange": [
        1769,
        1777
       ],
       "concept": "SYNTAX"
      },
      {
       "id": "67eba7c7-d2cd-409b-ad8e-9324c7754534",
       "type": "whitespace",
       "value": " ",
       "textRange": [
        1777,
        1778
       ],
       "concept": "SYNTAX"
      },
      {
       "id": "07f570d4-63de-4449-a745-4fde71ac5f46",
       "type": "word",
       "value": "його",
       "textRange": [
        1778,
        1782
       ],
       "concept": "SYNTAX"
      },
      {
       "id": "e113209c-d664-48fb-9b22-b3887e13bd5d",
       "type": "whitespace",
       "value": " ",
       "textRange": [
        1782,
        1783
       ],
       "concept": "SYNTAX"
      },
      {
       "id": "c92fcf52-c189-4e6b-9240-db02d5cd99a1",
       "type": "word",
       "value": "поставили",
       "textRange": [
        1783,
        1792
       ],
       "concept": "SYNTAX"
      },
      {
       "id": "8fde374e-44af-482c-b5c7-036c6c9bd063",
       "type": "whitespace",
       "value": " ",
       "textRange": [
        1792,
        1793
       ],
       "concept": "SYNTAX"
      },
      {
       "id": "fb4c9eb4-9eda-422d-ab85-f9a10f454e13",
       "type": "word",
       "value": "некоректно",
       "textRange": [
        1793,
        1803
       ],
       "concept": "SYNTAX"
      }
     ],
     "value": " якщо пацієнту його поставили некоректно",
     "concept": "SYNTAX"
    },
    {
     "id": "5f51986d-97a4-4054-8972-6b29c53010bf",
     "type": "punctuation",
     "value": ",",
     "textRange": [
      1803,
      1804
     ],
     "concept": "SYNTAX"
    },
    {
     "id": "9e60b4f7-76d9-4643-aa8f-b3b5da2fbab1",
     "type": "subSentence",
     "childs": [
      {
       "id": "8be62b73-5168-4547-9664-aa4d39f0df30",
       "type": "whitespace",
       "value": " ",
       "textRange": [
        1804,
        1805
       ],
       "concept": "SYNTAX"
      },
      {
       "id": "8704b3cd-32bf-4b96-9f28-a790317549d9",
       "type": "word",
       "value": "порушуючи",
       "textRange": [
        1805,
        1814
       ],
       "concept": "SYNTAX"
      },
      {
       "id": "0d79a461-6bec-44a8-84c9-45b88022005d",
       "type": "whitespace",
       "value": " ",
       "textRange": [
        1814,
        1815
       ],
       "concept": "SYNTAX"
      },
      {
       "id": "bd64c2a6-32c4-4001-b983-ea419de5f5be",
       "type": "word",
       "value": "правила",
       "textRange": [
        1815,
        1822
       ],
       "concept": "SYNTAX"
      },
      {
       "id": "ac5f9292-4e4b-4a5f-bb0f-32743354e95b",
       "type": "whitespace",
       "value": " ",
       "textRange": [
        1822,
        1823
       ],
       "concept": "SYNTAX"
      },
      {
       "id": "c38d3a0d-39a0-46a1-94b4-77bb8949f280",
       "type": "word",
       "value": "і",
       "textRange": [
        1823,
        1824
       ],
       "concept": "SYNTAX"
      },
      {
       "id": "ac01dfcb-00a8-4d96-a4f6-46e4f3c3b551",
       "type": "whitespace",
       "value": " ",
       "textRange": [
        1824,
        1825
       ],
       "concept": "SYNTAX"
      },
      {
       "id": "c4330f49-514f-4b09-8ae8-9f14d8962367",
       "type": "word",
       "value": "гігієнічні",
       "textRange": [
        1825,
        1835
       ],
       "concept": "SYNTAX"
      },
      {
       "id": "de8b1122-b742-426c-b87a-18d6bf13aa4e",
       "type": "whitespace",
       "value": " ",
       "textRange": [
        1835,
        1836
       ],
       "concept": "SYNTAX"
      },
      {
       "id": "8dafb6d4-766b-4827-a5aa-21d49518e41a",
       "type": "word",
       "value": "норми",
       "textRange": [
        1836,
        1841
       ],
       "concept": "SYNTAX"
      }
     ],
     "value": " порушуючи правила і гігієнічні норми",
     "concept": "SYNTAX"
    },
    {
     "id": "70862fb9-6afd-4147-9fa4-2cc4c1db208a",
     "type": "punctuation",
     "value": ".",
     "textRange": [
      1841,
      1842
     ],
     "concept": "SYNTAX"
    },
    {
     "id": "49ff2003-d74f-4379-bda5-98fb4e72d28d",
     "type": "punctuation",
     "value": "\n",
     "textRange": [
      1842,
      1843
     ],
     "concept": "SYNTAX"
    }
   ],
   "value": " Спричинити хворобу можуть віруси, гельмінти (паразити) і навіть сечовий катетер, якщо пацієнту його поставили некоректно, порушуючи правила і гігієнічні норми.",
   "concept": "SYNTAX"
  }
 ],
 "value": "Найбільш активні збудники інфекцій сечових шляхів — кишкова паличка, або ентерокок, іноді провокатором запальних процесів стає стафілокок Спричинити хворобу можуть віруси, гельмінти (паразити) і навіть сечовий катетер, якщо пацієнту його поставили некоректно, порушуючи правила і гігієнічні норми.",
 "concept": "SYNTAX"
}