{
 "id": "780bc30a-d6a5-46b1-9046-3c7979e75c86",
 "type": "paragraph",
 "childs": [
  {
   "id": "63c0636d-d5f4-4b77-90b7-0f2461df8990",
   "type": "sentence",
   "childs": [
    {
     "id": "f871889b-5bc3-40f3-b804-f6d663f24c0e",
     "type": "subSentence",
     "childs": [
      {
       "id": "bff0f077-b04c-4431-bf41-cc71714f5c92",
       "type": "word",
       "value": "Ось",
       "textRange": [
        0,
        3
       ],
       "concept": "SYNTAX"
      },
      {
       "id": "b8956e1b-9e4a-4347-860f-662cc19e7c0c",
       "type": "whitespace",
       "value": " ",
       "textRange": [
        3,
        4
       ],
       "concept": "SYNTAX"
      },
      {
       "id": "7bed3b59-80f0-41aa-9a1b-7bc11db439ac",
       "type": "word",
       "value": "у",
       "textRange": [
        4,
        5
       ],
       "concept": "SYNTAX"
      },
      {
       "id": "45031f53-23d5-4973-963d-20e5708e3741",
       "type": "whitespace",
       "value": " ",
       "textRange": [
        5,
        6
       ],
       "concept": "SYNTAX"
      },
      {
       "id": "42adece0-49ae-490d-b9dc-d96a8e1095f8",
       "type": "word",
       "value": "що",
       "textRange": [
        6,
        8
       ],
       "concept": "SYNTAX"
      },
      {
       "id": "3362ef78-f0b7-4fd4-9ff4-87e27176b9fd",
       "type": "whitespace",
       "value": " ",
       "textRange": [
        8,
        9
       ],
       "concept": "SYNTAX"
      },
      {
       "id": "4a81610d-6cd9-4875-986a-bba69fae86eb",
       "type": "word",
       "value": "вірили",
       "textRange": [
        9,
        15
       ],
       "concept": "SYNTAX"
      },
      {
       "id": "6cbd2892-c1e2-4176-b096-26d661660076",
       "type": "whitespace",
       "value": " ",
       "textRange": [
        15,
        16
       ],
       "concept": "SYNTAX"
      },
      {
       "id": "51bcb4b0-fe50-45a5-93d0-1d5c0413dbdb",
       "type": "word",
       "value": "люди",
       "textRange": [
        16,
        20
       ],
       "concept": "SYNTAX"
      },
      {
       "id": "4627865e-6714-437c-aac0-2caa46dedfc2",
       "type": "whitespace",
       "value": " ",
       "textRange": [
        20,
        21
       ],
       "concept": "SYNTAX"
      },
      {
       "id": "4489bf7a-1edf-4110-9128-a014a8f3c0a3",
       "type": "word",
       "value": "в",
       "textRange": [
        21,
        22
       ],
       "concept": "SYNTAX"
      },
      {
       "id": "5d0286d0-6fbd-45f9-a8e4-68861597ed90",
       "type": "whitespace",
       "value": " ",
       "textRange": [
        22,
        23
       ],
       "concept": "SYNTAX"
      },
      {
       "id": "8519406c-e386-43ff-9242-ac8deb080f94",
       "type": "word",
       "value": "тому",
       "textRange": [
        23,
        27
       ],
       "concept": "SYNTAX"
      },
      {
       "id": "f70ac934-c928-45ca-a11a-634e00f0fb75",
       "type": "whitespace",
       "value": " ",
       "textRange": [
        27,
        28
       ],
       "concept": "SYNTAX"
      },
      {
       "id": "4420ef3a-d783-493d-ac71-93fea4a285c7",
       "type": "word",
       "value": "краї",
       "textRange": [
        28,
        32
       ],
       "concept": "SYNTAX"
      }
     ],
     "value": "Ось у що вірили люди в тому краї",
     "concept": "SYNTAX"
    },
    {
     "id": "c856153d-cef8-48b3-97cf-f58be5c56b45",
     "type": "punctuation",
     "value": ".",
     "textRange": [
      32,
      33
     ],
     "concept": "SYNTAX"
    }
   ],
   "value": "Ось у що вірили люди в тому краї",
   "concept": "SYNTAX"
  },
  {
   "id": "6b74d46b-f52b-4bf5-94cf-a7b3cdcc790e",
   "type": "sentence",
   "childs": [
    {
     "id": "27025aff-27b0-42cf-ac4a-34a954fb58b4",
     "type": "subSentence",
     "childs": [
      {
       "id": "6bb51f4c-1100-468b-a365-1d6e9f12a688",
       "type": "whitespace",
       "value": " ",
       "textRange": [
        33,
        34
       ],
       "concept": "SYNTAX"
      },
      {
       "id": "ae4731ab-3c30-43a1-b2ba-5a8d65ba36ca",
       "type": "word",
       "value": "Але",
       "textRange": [
        34,
        37
       ],
       "concept": "SYNTAX"
      },
      {
       "id": "456d072c-40f9-41b5-93fe-3795e4ce095d",
       "type": "whitespace",
       "value": " ",
       "textRange": [
        37,
        38
       ],
       "concept": "SYNTAX"
      },
      {
       "id": "c29534ac-cf43-4ee9-8845-307c67ed1f16",
       "type": "word",
       "value": "все",
       "textRange": [
        38,
        41
       ],
       "concept": "SYNTAX"
      },
      {
       "id": "2df08f10-2b91-4fc7-adec-49a549145e03",
       "type": "whitespace",
       "value": " ",
       "textRange": [
        41,
        42
       ],
       "concept": "SYNTAX"
      },
      {
       "id": "ad93abff-c3ba-4914-9862-6a26c70efbcc",
       "type": "word",
       "value": "одно",
       "textRange": [
        42,
        46
       ],
       "concept": "SYNTAX"
      },
      {
       "id": "ba835a3f-bf4f-4837-b51e-aca7f123ab4a",
       "type": "whitespace",
       "value": " ",
       "textRange": [
        46,
        47
       ],
       "concept": "SYNTAX"
      },
      {
       "id": "6f6e1b59-8a52-48cb-8d85-5c219cd7a7ed",
       "type": "word",
       "value": "як",
       "textRange": [
        47,
        49
       ],
       "concept": "SYNTAX"
      },
      {
       "id": "c6580bd1-7e58-4a08-bb88-b1ac7d4d41d0",
       "type": "whitespace",
       "value": " ",
       "textRange": [
        49,
        50
       ],
       "concept": "SYNTAX"
      },
      {
       "id": "1781ba0d-714b-4081-a54f-184996901c67",
       "type": "word",
       "value": "чули",
       "textRange": [
        50,
        54
       ],
       "concept": "SYNTAX"
      }
     ],
     "value": " Але все одно як чули",
     "concept": "SYNTAX"
    },
    {
     "id": "269b61b5-1e5f-4061-a30e-2e2cf878af44",
     "type": "punctuation",
     "value": ",",
     "textRange": [
      54,
      55
     ],
     "concept": "SYNTAX"
    },
    {
     "id": "f396e1a1-116d-49c5-acf6-0af535abafe8",
     "type": "subSentence",
     "childs": [
      {
       "id": "b10bb933-57b5-4f7a-a2a5-e91dacb0d216",
       "type": "whitespace",
       "value": " ",
       "textRange": [
        55,
        56
       ],
       "concept": "SYNTAX"
      },
      {
       "id": "8e39864a-244d-4b00-bbc4-57d2a8be6283",
       "type": "word",
       "value": "що",
       "textRange": [
        56,
        58
       ],
       "concept": "SYNTAX"
      },
      {
       "id": "a70c5416-71fc-47fb-befa-288bfef94f00",
       "type": "whitespace",
       "value": " ",
       "textRange": [
        58,
        59
       ],
       "concept": "SYNTAX"
      },
      {
       "id": "ce0b557b-6265-4516-bb98-9c937dc4eff8",
       "type": "word",
       "value": "котрогось",
       "textRange": [
        59,
        68
       ],
       "concept": "SYNTAX"
      },
      {
       "id": "24bb6dee-95e7-48de-b101-4bb02d4e47b1",
       "type": "whitespace",
       "value": " ",
       "textRange": [
        68,
        69
       ],
       "concept": "SYNTAX"
      },
      {
       "id": "eef2ea52-0a0a-4c6a-8491-ceecfd981ff6",
       "type": "word",
       "value": "забрали",
       "textRange": [
        69,
        76
       ],
       "concept": "SYNTAX"
      },
      {
       "id": "6988ec23-d4d2-493e-a785-043e318b7d58",
       "type": "whitespace",
       "value": " ",
       "textRange": [
        76,
        77
       ],
       "concept": "SYNTAX"
      },
      {
       "id": "7cc9b466-bc8a-48bf-9ba2-f611003520b5",
       "type": "word",
       "value": "до",
       "textRange": [
        77,
        79
       ],
       "concept": "SYNTAX"
      },
      {
       "id": "75d9987b-ea57-49e0-b5f6-f657e0e634fe",
       "type": "whitespace",
       "value": " ",
       "textRange": [
        79,
        80
       ],
       "concept": "SYNTAX"
      },
      {
       "id": "57a3a89a-d6bb-4b6f-987f-d1c0641f8252",
       "type": "word",
       "value": "королівського",
       "textRange": [
        80,
        93
       ],
       "concept": "SYNTAX"
      },
      {
       "id": "bc7dd68c-1c6d-4192-aaea-ae7b15b7b8e4",
       "type": "whitespace",
       "value": " ",
       "textRange": [
        93,
        94
       ],
       "concept": "SYNTAX"
      },
      {
       "id": "d6876306-f487-4454-9c66-ecf0d01b57ce",
       "type": "word",
       "value": "війська",
       "textRange": [
        94,
        101
       ],
       "concept": "SYNTAX"
      }
     ],
     "value": " що котрогось забрали до королівського війська",
     "concept": "SYNTAX"
    },
    {
     "id": "45672343-6a3d-4145-974a-f397286402f8",
     "type": "punctuation",
     "value": ",",
     "textRange": [
      101,
      102
     ],
     "concept": "SYNTAX"
    },
    {
     "id": "fac7b3a7-e97d-4345-a3ef-385b9d452830",
     "type": "subSentence",
     "childs": [
      {
       "id": "bc23dedb-4b92-4145-a256-a4240da9dc3c",
       "type": "whitespace",
       "value": " ",
       "textRange": [
        102,
        103
       ],
       "concept": "SYNTAX"
      },
      {
       "id": "a4978151-7b19-4267-8200-40231c5ff34b",
       "type": "word",
       "value": "а",
       "textRange": [
        103,
        104
       ],
       "concept": "SYNTAX"
      },
      {
       "id": "ef1867cb-894c-40a6-850e-5fa549780c11",
       "type": "whitespace",
       "value": " ",
       "textRange": [
        104,
        105
       ],
       "concept": "SYNTAX"
      },
      {
       "id": "15a99d26-0034-4425-b2c6-b71e6e35145c",
       "type": "word",
       "value": "котрусь",
       "textRange": [
        105,
        112
       ],
       "concept": "SYNTAX"
      },
      {
       "id": "07d5f929-b3bf-4077-95f0-f2a2c7128d73",
       "type": "whitespace",
       "value": " ",
       "textRange": [
        112,
        113
       ],
       "concept": "SYNTAX"
      },
      {
       "id": "d6d76370-9280-497e-b923-d07d7b00a7b4",
       "type": "whitespace",
       "value": "—",
       "textRange": [
        113,
        114
       ],
       "concept": "SYNTAX"
      },
      {
       "id": "25227ae4-26b0-45f2-9559-b9e4d703e03a",
       "type": "whitespace",
       "value": " ",
       "textRange": [
        114,
        115
       ],
       "concept": "SYNTAX"
      },
      {
       "id": "19287b71-98b2-4e27-abca-6941b6ac51c9",
       "type": "word",
       "value": "до",
       "textRange": [
        115,
        117
       ],
       "concept": "SYNTAX"
      },
      {
       "id": "397743a8-bfd0-4cd7-9a6d-0bca85c89706",
       "type": "whitespace",
       "value": " ",
       "textRange": [
        117,
        118
       ],
       "concept": "SYNTAX"
      },
      {
       "id": "f39d6102-7212-4463-af28-6fb7b06556a4",
       "type": "word",
       "value": "покоїв",
       "textRange": [
        118,
        124
       ],
       "concept": "SYNTAX"
      },
      {
       "id": "83a3289f-296c-40e6-a510-5450e428d763",
       "type": "whitespace",
       "value": " ",
       "textRange": [
        124,
        125
       ],
       "concept": "SYNTAX"
      },
      {
       "id": "be96aa28-837d-4c97-b945-1dfd2e92792c",
       "type": "word",
       "value": "королівни",
       "textRange": [
        125,
        134
       ],
       "concept": "SYNTAX"
      }
     ],
     "value": " а котрусь — до покоїв королівни",
     "concept": "SYNTAX"
    },
    {
     "id": "bfe9d427-679d-47d5-8e2b-c7be23721688",
     "type": "punctuation",
     "value": ",",
     "textRange": [
      134,
      135
     ],
     "concept": "SYNTAX"
    },
    {
     "id": "2240cff4-c3a2-43ab-906e-ca880a1b9d92",
     "type": "subSentence",
     "childs": [
      {
       "id": "0a01153c-5f3b-4cb3-8c40-13cf9515458f",
       "type": "whitespace",
       "value": " ",
       "textRange": [
        135,
        136
       ],
       "concept": "SYNTAX"
      },
      {
       "id": "dd68c089-5132-4249-ad7a-f01f5b7452c1",
       "type": "word",
       "value": "серце",
       "textRange": [
        136,
        141
       ],
       "concept": "SYNTAX"
      },
      {
       "id": "9f56f864-3f7d-465d-ab4d-c99d2f609698",
       "type": "whitespace",
       "value": " ",
       "textRange": [
        141,
        142
       ],
       "concept": "SYNTAX"
      },
      {
       "id": "5072be8b-4350-4b8b-8d3d-0a3da2c604a9",
       "type": "word",
       "value": "падало",
       "textRange": [
        142,
        148
       ],
       "concept": "SYNTAX"
      },
      {
       "id": "d32dd4a8-f627-4e4f-b62e-4feab9f2819f",
       "type": "whitespace",
       "value": " ",
       "textRange": [
        148,
        149
       ],
       "concept": "SYNTAX"
      },
      {
       "id": "995e03e3-0307-4262-a21c-2e0fbab6fc1d",
       "type": "word",
       "value": "мало",
       "textRange": [
        149,
        153
       ],
       "concept": "SYNTAX"
      },
      {
       "id": "a291f1c3-488d-492e-ac58-6a4325bd50b4",
       "type": "whitespace",
       "value": " ",
       "textRange": [
        153,
        154
       ],
       "concept": "SYNTAX"
      },
      {
       "id": "a05fcf8c-a7c3-4308-aac8-57553c995007",
       "type": "word",
       "value": "не",
       "textRange": [
        154,
        156
       ],
       "concept": "SYNTAX"
      },
      {
       "id": "3d0401d5-ef95-4364-abfa-16282a08852c",
       "type": "whitespace",
       "value": " ",
       "textRange": [
        156,
        157
       ],
       "concept": "SYNTAX"
      },
      {
       "id": "d5e185f0-d65b-44ec-8351-69ea6d71a5a2",
       "type": "word",
       "value": "до",
       "textRange": [
        157,
        159
       ],
       "concept": "SYNTAX"
      },
      {
       "id": "92a4af16-1e56-473e-810e-5ced0193039a",
       "type": "whitespace",
       "value": " ",
       "textRange": [
        159,
        160
       ],
       "concept": "SYNTAX"
      },
      {
       "id": "f9ae44bf-8fe0-4cc8-b3dc-1288ed269929",
       "type": "word",
       "value": "п’ят",
       "textRange": [
        160,
        164
       ],
       "concept": "SYNTAX"
      }
     ],
     "value": " серце падало мало не до п’ят",
     "concept": "SYNTAX"
    },
    {
     "id": "36640efd-65ce-475b-82db-e66bca578e35",
     "type": "punctuation",
     "value": ",",
     "textRange": [
      164,
      165
     ],
     "concept": "SYNTAX"
    },
    {
     "id": "1cd358f3-77bd-44e4-9660-54b333a11eaf",
     "type": "subSentence",
     "childs": [
      {
       "id": "2cd9599b-e27e-4186-87b2-1f17ce59e800",
       "type": "whitespace",
       "value": " ",
       "textRange": [
        165,
        166
       ],
       "concept": "SYNTAX"
      },
      {
       "id": "ee67e8d9-51be-4757-af13-8c2bd3ffdc27",
       "type": "word",
       "value": "у",
       "textRange": [
        166,
        167
       ],
       "concept": "SYNTAX"
      },
      {
       "id": "759d5886-5cbb-4c84-bd52-d1aacf2003f2",
       "type": "whitespace",
       "value": " ",
       "textRange": [
        167,
        168
       ],
       "concept": "SYNTAX"
      },
      {
       "id": "8995ee07-54f7-46b4-802d-3e04c663ee44",
       "type": "word",
       "value": "грудях",
       "textRange": [
        168,
        174
       ],
       "concept": "SYNTAX"
      },
      {
       "id": "0b8eef95-6cdc-4124-90ca-355638f30700",
       "type": "whitespace",
       "value": " ",
       "textRange": [
        174,
        175
       ],
       "concept": "SYNTAX"
      },
      {
       "id": "61e6deb4-d67d-40f9-9791-52c5b9a1762f",
       "type": "word",
       "value": "усе",
       "textRange": [
        175,
        178
       ],
       "concept": "SYNTAX"
      },
      {
       "id": "fa98d28b-dcd6-40e7-a9d1-bb687ccdaeca",
       "type": "whitespace",
       "value": " ",
       "textRange": [
        178,
        179
       ],
       "concept": "SYNTAX"
      },
      {
       "id": "75f2fe0c-f73b-493e-8a40-405ac05c4018",
       "type": "word",
       "value": "холонуло",
       "textRange": [
        179,
        187
       ],
       "concept": "SYNTAX"
      }
     ],
     "value": " у грудях усе холонуло",
     "concept": "SYNTAX"
    },
    {
     "id": "8422d701-9b4e-4aa4-95e2-335023de08df",
     "type": "punctuation",
     "value": ",",
     "textRange": [
      187,
      188
     ],
     "concept": "SYNTAX"
    },
    {
     "id": "438f8273-988d-4b29-9b0e-75406ec2e838",
     "type": "subSentence",
     "childs": [
      {
       "id": "dfe61fcc-f008-4d9f-9ceb-7f514fec4dec",
       "type": "whitespace",
       "value": " ",
       "textRange": [
        188,
        189
       ],
       "concept": "SYNTAX"
      },
      {
       "id": "d830f140-00d5-4626-9e81-9a44ff012629",
       "type": "word",
       "value": "світ",
       "textRange": [
        189,
        193
       ],
       "concept": "SYNTAX"
      },
      {
       "id": "2160abca-7e59-432a-ba80-c1a5a1b2aa30",
       "type": "whitespace",
       "value": " ",
       "textRange": [
        193,
        194
       ],
       "concept": "SYNTAX"
      },
      {
       "id": "387660d0-490f-4b0d-aeac-1283c5942295",
       "type": "word",
       "value": "перед",
       "textRange": [
        194,
        199
       ],
       "concept": "SYNTAX"
      },
      {
       "id": "c0d260a7-2ad2-4745-a941-c4a3c8fc76d0",
       "type": "whitespace",
       "value": " ",
       "textRange": [
        199,
        200
       ],
       "concept": "SYNTAX"
      },
      {
       "id": "7e9e7ed7-544b-47df-878a-70406983553b",
       "type": "word",
       "value": "очима",
       "textRange": [
        200,
        205
       ],
       "concept": "SYNTAX"
      },
      {
       "id": "02a09072-9ae4-4f2d-95b6-f446b72315eb",
       "type": "whitespace",
       "value": " ",
       "textRange": [
        205,
        206
       ],
       "concept": "SYNTAX"
      },
      {
       "id": "8d10a5f8-6d0b-42c9-acd3-1ba6719fe1bc",
       "type": "word",
       "value": "робився",
       "textRange": [
        206,
        213
       ],
       "concept": "SYNTAX"
      },
      {
       "id": "f89e70f5-6bfd-458f-8dd6-e728fb1d4720",
       "type": "whitespace",
       "value": " ",
       "textRange": [
        213,
        214
       ],
       "concept": "SYNTAX"
      },
      {
       "id": "297be050-3172-4247-b95b-2201e636806b",
       "type": "word",
       "value": "темним",
       "textRange": [
        214,
        220
       ],
       "concept": "SYNTAX"
      }
     ],
     "value": " світ перед очима робився темним",
     "concept": "SYNTAX"
    },
    {
     "id": "a0b7e903-f53e-4b43-b218-93db5a0ca6f5",
     "type": "punctuation",
     "value": ".",
     "textRange": [
      220,
      221
     ],
     "concept": "SYNTAX"
    }
   ],
   "value": " Але все одно як чули, що котрогось забрали до королівського війська, а котрусь — до покоїв королівни, серце падало мало не до п’ят, у грудях усе холонуло, світ перед очима робився темним",
   "concept": "SYNTAX"
  },
  {
   "id": "f1d68b3f-6c27-4d40-9e98-6b160af93c13",
   "type": "sentence",
   "childs": [
    {
     "id": "2a8da1c8-5c10-4e6e-945c-5c96b162d06f",
     "type": "subSentence",
     "childs": [
      {
       "id": "a5b7515e-d289-4e32-b4c0-85e15f1b0fb4",
       "type": "whitespace",
       "value": " ",
       "textRange": [
        221,
        222
       ],
       "concept": "SYNTAX"
      },
      {
       "id": "86cbd25c-fd51-4555-a3ac-6cc21dda65ec",
       "type": "word",
       "value": "Відтак",
       "textRange": [
        222,
        228
       ],
       "concept": "SYNTAX"
      },
      {
       "id": "7e09f499-ec54-4ab1-bf1c-356a7a115472",
       "type": "whitespace",
       "value": " ",
       "textRange": [
        228,
        229
       ],
       "concept": "SYNTAX"
      },
      {
       "id": "f55378df-6306-412d-a931-5fff3c353e0e",
       "type": "word",
       "value": "однаково",
       "textRange": [
        229,
        237
       ],
       "concept": "SYNTAX"
      },
      {
       "id": "5ee80e08-7ce1-4de8-8893-b84f34486c26",
       "type": "whitespace",
       "value": " ",
       "textRange": [
        237,
        238
       ],
       "concept": "SYNTAX"
      },
      {
       "id": "1f04b73f-b4e7-4f51-9533-d7b7ebf49219",
       "type": "word",
       "value": "ніхто",
       "textRange": [
        238,
        243
       ],
       "concept": "SYNTAX"
      },
      {
       "id": "a89b346d-73a3-4b1c-89c9-46a79ab0232d",
       "type": "whitespace",
       "value": " ",
       "textRange": [
        243,
        244
       ],
       "concept": "SYNTAX"
      },
      {
       "id": "9ad80e47-1e4b-40d8-acd2-d846ca0cbbfe",
       "type": "word",
       "value": "не",
       "textRange": [
        244,
        246
       ],
       "concept": "SYNTAX"
      },
      {
       "id": "ba1b3b02-0185-4790-8b9c-37b4db677927",
       "type": "whitespace",
       "value": " ",
       "textRange": [
        246,
        247
       ],
       "concept": "SYNTAX"
      },
      {
       "id": "d88af70b-da2c-4ae0-9cb7-80d6cf3956c1",
       "type": "word",
       "value": "міг",
       "textRange": [
        247,
        250
       ],
       "concept": "SYNTAX"
      },
      {
       "id": "84ebc3de-eebf-45e7-bc2d-0533c7d8dc07",
       "type": "whitespace",
       "value": " ",
       "textRange": [
        250,
        251
       ],
       "concept": "SYNTAX"
      },
      {
       "id": "13c4de25-ef60-4cdf-b844-705126b15835",
       "type": "word",
       "value": "нічого",
       "textRange": [
        251,
        257
       ],
       "concept": "SYNTAX"
      },
      {
       "id": "a2491945-a08b-49a3-9e9a-8b37184a6795",
       "type": "whitespace",
       "value": " ",
       "textRange": [
        257,
        258
       ],
       "concept": "SYNTAX"
      },
      {
       "id": "f2e283a7-2460-4e6a-be6f-80ad0ed275e6",
       "type": "word",
       "value": "вдіяти",
       "textRange": [
        258,
        264
       ],
       "concept": "SYNTAX"
      }
     ],
     "value": " Відтак однаково ніхто не міг нічого вдіяти",
     "concept": "SYNTAX"
    },
    {
     "id": "9fbdbfc7-d269-4eb8-95d9-faab33a14c0d",
     "type": "punctuation",
     "value": ".",
     "textRange": [
      264,
      265
     ],
     "concept": "SYNTAX"
    }
   ],
   "value": " Відтак однаково ніхто не міг нічого вдіяти",
   "concept": "SYNTAX"
  },
  {
   "id": "a9969762-ac96-4fa1-baf2-de25e64173e1",
   "type": "sentence",
   "childs": [
    {
     "id": "9cf1adf8-f279-4a42-ac44-e69d815cc033",
     "type": "subSentence",
     "childs": [
      {
       "id": "e5eb38ac-85b1-40ac-b783-a1dba003a4ac",
       "type": "whitespace",
       "value": " ",
       "textRange": [
        265,
        266
       ],
       "concept": "SYNTAX"
      },
      {
       "id": "732f8602-3d5a-41aa-820c-a97fd2d5db5b",
       "type": "word",
       "value": "Такі",
       "textRange": [
        266,
        270
       ],
       "concept": "SYNTAX"
      },
      {
       "id": "be66b769-e04f-4e54-8611-5e2ce7357973",
       "type": "whitespace",
       "value": " ",
       "textRange": [
        270,
        271
       ],
       "concept": "SYNTAX"
      },
      {
       "id": "fb2624d5-3bc0-4893-9b6d-3c4e355c6d83",
       "type": "word",
       "value": "порядки",
       "textRange": [
        271,
        278
       ],
       "concept": "SYNTAX"
      },
      {
       "id": "2c17f54d-d995-4d6a-818c-b79416ad8144",
       "type": "whitespace",
       "value": " ",
       "textRange": [
        278,
        279
       ],
       "concept": "SYNTAX"
      },
      {
       "id": "8f6ca74f-0206-40fe-a2f3-604ca474c0d2",
       "type": "word",
       "value": "завів",
       "textRange": [
        279,
        284
       ],
       "concept": "SYNTAX"
      },
      {
       "id": "db9a7b89-6773-4e4f-b467-9678fde9aeac",
       "type": "whitespace",
       "value": " ",
       "textRange": [
        284,
        285
       ],
       "concept": "SYNTAX"
      },
      {
       "id": "4f3d92d6-cdbd-4e09-907c-2bcb45db61b2",
       "type": "word",
       "value": "тамтешній",
       "textRange": [
        285,
        294
       ],
       "concept": "SYNTAX"
      },
      {
       "id": "3217fe44-d55d-43e7-a276-e1b18b3acd27",
       "type": "whitespace",
       "value": " ",
       "textRange": [
        294,
        295
       ],
       "concept": "SYNTAX"
      },
      {
       "id": "3608b422-d576-47b1-ba08-1161bc5320f4",
       "type": "word",
       "value": "пан",
       "textRange": [
        295,
        298
       ],
       "concept": "SYNTAX"
      }
     ],
     "value": " Такі порядки завів тамтешній пан",
     "concept": "SYNTAX"
    },
    {
     "id": "a013aedf-5b2e-4edd-8ea0-c1abe9912950",
     "type": "punctuation",
     "value": ",",
     "textRange": [
      298,
      299
     ],
     "concept": "SYNTAX"
    },
    {
     "id": "55c9b074-84fc-4bea-9d19-6266774ffef7",
     "type": "subSentence",
     "childs": [
      {
       "id": "36557bee-68a8-41e3-bc55-7e0586e35424",
       "type": "whitespace",
       "value": " ",
       "textRange": [
        299,
        300
       ],
       "concept": "SYNTAX"
      },
      {
       "id": "81354110-1127-45b4-b7b0-4a9e39732918",
       "type": "word",
       "value": "і",
       "textRange": [
        300,
        301
       ],
       "concept": "SYNTAX"
      },
      {
       "id": "f18658c7-8958-449c-b890-c499361307fd",
       "type": "whitespace",
       "value": " ",
       "textRange": [
        301,
        302
       ],
       "concept": "SYNTAX"
      },
      {
       "id": "70d62b06-3867-4f9f-b7b2-201c53ad47bb",
       "type": "word",
       "value": "всі",
       "textRange": [
        302,
        305
       ],
       "concept": "SYNTAX"
      },
      {
       "id": "5e540776-fbe0-4e40-a4f5-a10bd4b6b40d",
       "type": "whitespace",
       "value": " ",
       "textRange": [
        305,
        306
       ],
       "concept": "SYNTAX"
      },
      {
       "id": "157cca87-fbb7-4850-84a4-8f4f36bc46f9",
       "type": "word",
       "value": "довкола",
       "textRange": [
        306,
        313
       ],
       "concept": "SYNTAX"
      },
      {
       "id": "cb1411e8-9c68-491e-8fc4-5b573d8807aa",
       "type": "whitespace",
       "value": " ",
       "textRange": [
        313,
        314
       ],
       "concept": "SYNTAX"
      },
      {
       "id": "67857893-7941-41e1-878e-850ce38326e7",
       "type": "word",
       "value": "вважали",
       "textRange": [
        314,
        321
       ],
       "concept": "SYNTAX"
      },
      {
       "id": "122bb348-0ce3-4460-8383-bd52535dfa74",
       "type": "whitespace",
       "value": " ",
       "textRange": [
        321,
        322
       ],
       "concept": "SYNTAX"
      },
      {
       "id": "aad50ae0-fd89-4d6d-b740-1be45ee7c107",
       "type": "word",
       "value": "його",
       "textRange": [
        322,
        326
       ],
       "concept": "SYNTAX"
      },
      {
       "id": "9537cbe2-a122-4a48-a7f6-5d17904b7b84",
       "type": "whitespace",
       "value": " ",
       "textRange": [
        326,
        327
       ],
       "concept": "SYNTAX"
      },
      {
       "id": "e82d2501-22ca-4eaf-a837-95aec580c194",
       "type": "word",
       "value": "мудрим",
       "textRange": [
        327,
        333
       ],
       "concept": "SYNTAX"
      }
     ],
     "value": " і всі довкола вважали його мудрим",
     "concept": "SYNTAX"
    },
    {
     "id": "6ce373c0-3654-4ce4-a3e8-9ec1e91e4c48",
     "type": "punctuation",
     "value": ",",
     "textRange": [
      333,
      334
     ],
     "concept": "SYNTAX"
    },
    {
     "id": "6d456064-a31d-40a9-8b12-870c8600e4a9",
     "type": "subSentence",
     "childs": [
      {
       "id": "22b55d7d-b04e-46a9-8664-94286eb3312a",
       "type": "whitespace",
       "value": " ",
       "textRange": [
        334,
        335
       ],
       "concept": "SYNTAX"
      },
      {
       "id": "02e9f09d-13e2-4059-93c2-a035cca7acca",
       "type": "word",
       "value": "чесним",
       "textRange": [
        335,
        341
       ],
       "concept": "SYNTAX"
      },
      {
       "id": "2a8efffe-2a29-438f-9e67-13addbd27b63",
       "type": "whitespace",
       "value": " ",
       "textRange": [
        341,
        342
       ],
       "concept": "SYNTAX"
      },
      {
       "id": "1c01fe8c-c6aa-4961-84f3-3bf1d3e7b3b5",
       "type": "word",
       "value": "та",
       "textRange": [
        342,
        344
       ],
       "concept": "SYNTAX"
      },
      {
       "id": "25f30390-bcdb-4883-bd0c-4a75c261088f",
       "type": "whitespace",
       "value": " ",
       "textRange": [
        344,
        345
       ],
       "concept": "SYNTAX"
      },
      {
       "id": "33834204-5c47-4c1c-aa05-ba4e3f882896",
       "type": "word",
       "value": "благородним",
       "textRange": [
        345,
        356
       ],
       "concept": "SYNTAX"
      }
     ],
     "value": " чесним та благородним",
     "concept": "SYNTAX"
    },
    {
     "id": "8597371f-0776-404d-979b-fed9f24f0efd",
     "type": "punctuation",
     "value": ".",
     "textRange": [
      356,
      357
     ],
     "concept": "SYNTAX"
    },
    {
     "id": "41307944-ddd2-4c86-b8bc-8ef8da5d03b0",
     "type": "punctuation",
     "value": "\n",
     "textRange": [
      357,
      358
     ],
     "concept": "SYNTAX"
    }
   ],
   "value": " Такі порядки завів тамтешній пан, і всі довкола вважали його мудрим, чесним та благородним.",
   "concept": "SYNTAX"
  }
 ],
 "value": "Ось у що вірили люди в тому краї Але все одно як чули, що котрогось забрали до королівського війська, а котрусь — до покоїв королівни, серце падало мало не до п’ят, у грудях усе холонуло, світ перед очима робився темним Відтак однаково ніхто не міг нічого вдіяти Такі порядки завів тамтешній пан, і всі довкола вважали його мудрим, чесним та благородним.",
 "concept": "SYNTAX"
}