{
 "id": "f245c406-1676-4c50-8957-06c23beb2e20",
 "type": "paragraph",
 "childs": [
  {
   "id": "9d1fe60c-b0c3-48cc-acfc-73d65a58aeed",
   "type": "sentence",
   "childs": [
    {
     "id": "4ef0461c-28e8-4806-abca-5ab0d723aabc",
     "type": "subSentence",
     "childs": [
      {
       "id": "161fe9ee-0bbb-41e3-bbe4-4dfb6abc9529",
       "type": "word",
       "value": "-",
       "textRange": [
        1061,
        1062
       ],
       "concept": "SYNTAX"
      },
      {
       "id": "d65bae33-3fe0-4d31-bc26-af35c0f03b50",
       "type": "whitespace",
       "value": " ",
       "textRange": [
        1062,
        1063
       ],
       "concept": "SYNTAX"
      },
      {
       "id": "ba6f3b6a-6b25-461e-8034-72a9f6356376",
       "type": "word",
       "value": "Я",
       "textRange": [
        1063,
        1064
       ],
       "concept": "SYNTAX"
      },
      {
       "id": "0b0c9881-1555-4982-a0e5-21263836b124",
       "type": "whitespace",
       "value": " ",
       "textRange": [
        1064,
        1065
       ],
       "concept": "SYNTAX"
      },
      {
       "id": "bb40f24a-db09-47b6-8697-2954d267bb3c",
       "type": "word",
       "value": "тобі",
       "textRange": [
        1065,
        1069
       ],
       "concept": "SYNTAX"
      },
      {
       "id": "44437ea0-f682-46c6-b763-c8659177468b",
       "type": "whitespace",
       "value": " ",
       "textRange": [
        1069,
        1070
       ],
       "concept": "SYNTAX"
      },
      {
       "id": "b938559e-83d0-4170-9e7d-bf5e790935a6",
       "type": "word",
       "value": "скажу",
       "textRange": [
        1070,
        1075
       ],
       "concept": "SYNTAX"
      }
     ],
     "value": "- Я тобі скажу",
     "concept": "SYNTAX"
    },
    {
     "id": "745ea411-5ad2-49d1-a75b-307699d0d9aa",
     "type": "punctuation",
     "value": ",",
     "textRange": [
      1075,
      1076
     ],
     "concept": "SYNTAX"
    },
    {
     "id": "dc7393d6-70c1-4c03-9d08-b3544963253b",
     "type": "subSentence",
     "childs": [
      {
       "id": "9bda8b7c-97fa-48e8-8aa0-61d8e1aee77a",
       "type": "whitespace",
       "value": " ",
       "textRange": [
        1076,
        1077
       ],
       "concept": "SYNTAX"
      },
      {
       "id": "63d300fa-2c78-44c9-9076-a9ee76e02f02",
       "type": "word",
       "value": "але",
       "textRange": [
        1077,
        1080
       ],
       "concept": "SYNTAX"
      },
      {
       "id": "56847cca-6de9-4851-8dde-97165dc125ee",
       "type": "whitespace",
       "value": " ",
       "textRange": [
        1080,
        1081
       ],
       "concept": "SYNTAX"
      },
      {
       "id": "abf1f6f7-9dca-4cb2-9c52-cbb01fa4112f",
       "type": "word",
       "value": "ти",
       "textRange": [
        1081,
        1083
       ],
       "concept": "SYNTAX"
      },
      {
       "id": "a0b7c3e2-342c-40cf-a076-308d4a794093",
       "type": "whitespace",
       "value": " ",
       "textRange": [
        1083,
        1084
       ],
       "concept": "SYNTAX"
      },
      {
       "id": "ebee500c-9f0b-4928-948d-44fa0ae3459b",
       "type": "word",
       "value": "нікому",
       "textRange": [
        1084,
        1090
       ],
       "concept": "SYNTAX"
      },
      {
       "id": "a6f21da7-9684-4038-950d-6af1b9b0903e",
       "type": "whitespace",
       "value": " ",
       "textRange": [
        1090,
        1091
       ],
       "concept": "SYNTAX"
      },
      {
       "id": "b68adb57-b4ea-4141-89d5-ef0850dd0781",
       "type": "word",
       "value": "не",
       "textRange": [
        1091,
        1093
       ],
       "concept": "SYNTAX"
      },
      {
       "id": "09f4ff65-e600-4f6e-a377-9c28c815e8da",
       "type": "whitespace",
       "value": " ",
       "textRange": [
        1093,
        1094
       ],
       "concept": "SYNTAX"
      },
      {
       "id": "b2192c30-fdc5-4b78-96ab-29a1b61573b5",
       "type": "word",
       "value": "переповідай",
       "textRange": [
        1094,
        1105
       ],
       "concept": "SYNTAX"
      }
     ],
     "value": " але ти нікому не переповідай",
     "concept": "SYNTAX"
    },
    {
     "id": "0483a79a-fea4-4258-9ef9-0788f1367163",
     "type": "punctuation",
     "value": ",",
     "textRange": [
      1105,
      1106
     ],
     "concept": "SYNTAX"
    },
    {
     "id": "3f112cde-183f-4e3f-b9bd-de7edc13ffe1",
     "type": "subSentence",
     "childs": [
      {
       "id": "952d738e-058e-4d54-8d86-b484adff66b7",
       "type": "whitespace",
       "value": " ",
       "textRange": [
        1106,
        1107
       ],
       "concept": "SYNTAX"
      },
      {
       "id": "eb790ee2-1ebb-4d15-8a5e-af92d38f4ee7",
       "type": "word",
       "value": "бо",
       "textRange": [
        1107,
        1109
       ],
       "concept": "SYNTAX"
      },
      {
       "id": "54c843b4-5694-43c4-b1d6-79427e8a6b84",
       "type": "whitespace",
       "value": " ",
       "textRange": [
        1109,
        1110
       ],
       "concept": "SYNTAX"
      },
      {
       "id": "c2cd49ff-cb81-43ec-895b-ba7b5d766fa8",
       "type": "word",
       "value": "можна",
       "textRange": [
        1110,
        1115
       ],
       "concept": "SYNTAX"
      },
      {
       "id": "112e146d-507f-4599-9030-2bb7df3c301e",
       "type": "whitespace",
       "value": " ",
       "textRange": [
        1115,
        1116
       ],
       "concept": "SYNTAX"
      },
      {
       "id": "3ce2744c-309e-4086-aff2-ccff6b284365",
       "type": "word",
       "value": "зле",
       "textRange": [
        1116,
        1119
       ],
       "concept": "SYNTAX"
      },
      {
       "id": "cf875d2b-45fb-46b7-bdc6-d74fe4c6b2e0",
       "type": "whitespace",
       "value": " ",
       "textRange": [
        1119,
        1120
       ],
       "concept": "SYNTAX"
      },
      {
       "id": "53d2b640-80e6-45eb-8f26-7fe9cf0ecb33",
       "type": "word",
       "value": "напророчити",
       "textRange": [
        1120,
        1131
       ],
       "concept": "SYNTAX"
      }
     ],
     "value": " бо можна зле напророчити",
     "concept": "SYNTAX"
    },
    {
     "id": "159f537e-98ca-4ff3-92f0-4fa8b6f5ec74",
     "type": "punctuation",
     "value": ".",
     "textRange": [
      1131,
      1132
     ],
     "concept": "SYNTAX"
    }
   ],
   "value": "- Я тобі скажу, але ти нікому не переповідай, бо можна зле напророчити",
   "concept": "SYNTAX"
  },
  {
   "id": "a951bb1d-1f33-4788-9c9a-da2a6406c97f",
   "type": "sentence",
   "childs": [
    {
     "id": "38f26b57-6b4b-4100-bc9c-ba9c4042d065",
     "type": "subSentence",
     "childs": [
      {
       "id": "747a8644-0eac-45fc-9cea-9d054e88f883",
       "type": "whitespace",
       "value": " ",
       "textRange": [
        1132,
        1133
       ],
       "concept": "SYNTAX"
      },
      {
       "id": "428fbeae-3b39-4c13-ae35-8a118a0f9548",
       "type": "word",
       "value": "Я",
       "textRange": [
        1133,
        1134
       ],
       "concept": "SYNTAX"
      },
      {
       "id": "931ea12c-f396-4cd7-8486-0f00b0f0a4bf",
       "type": "whitespace",
       "value": " ",
       "textRange": [
        1134,
        1135
       ],
       "concept": "SYNTAX"
      },
      {
       "id": "6b1677a5-1628-423d-bdbe-65755e93090c",
       "type": "word",
       "value": "беру",
       "textRange": [
        1135,
        1139
       ],
       "concept": "SYNTAX"
      },
      {
       "id": "6fc025ac-a3f2-46d0-8937-c16d36be9217",
       "type": "whitespace",
       "value": " ",
       "textRange": [
        1139,
        1140
       ],
       "concept": "SYNTAX"
      },
      {
       "id": "624cb6d7-dfee-4b0d-8e15-0ce9bb9e0ddb",
       "type": "word",
       "value": "мед",
       "textRange": [
        1140,
        1143
       ],
       "concept": "SYNTAX"
      }
     ],
     "value": " Я беру мед",
     "concept": "SYNTAX"
    },
    {
     "id": "505050d2-8d0d-4b60-b8ba-72418a2a341f",
     "type": "punctuation",
     "value": ",",
     "textRange": [
      1143,
      1144
     ],
     "concept": "SYNTAX"
    },
    {
     "id": "bd658c48-cb60-4f9a-96b3-1b2a627ef2c2",
     "type": "subSentence",
     "childs": [
      {
       "id": "bb3810a9-145a-457d-9dcb-77688921ee0c",
       "type": "whitespace",
       "value": " ",
       "textRange": [
        1144,
        1145
       ],
       "concept": "SYNTAX"
      },
      {
       "id": "9001c597-1b5a-4e77-b355-40b648412d7a",
       "type": "word",
       "value": "намащую",
       "textRange": [
        1145,
        1152
       ],
       "concept": "SYNTAX"
      },
      {
       "id": "366c09c0-ae1c-4ae3-82dd-86e73264dfb2",
       "type": "whitespace",
       "value": " ",
       "textRange": [
        1152,
        1153
       ],
       "concept": "SYNTAX"
      },
      {
       "id": "0481e9c5-deb9-4707-994c-7e1cbe562b92",
       "type": "word",
       "value": "ним",
       "textRange": [
        1153,
        1156
       ],
       "concept": "SYNTAX"
      },
      {
       "id": "a366bf25-0917-452a-92b1-84652f1d21f8",
       "type": "whitespace",
       "value": " ",
       "textRange": [
        1156,
        1157
       ],
       "concept": "SYNTAX"
      },
      {
       "id": "921675e2-7770-4ff8-8e1f-d29535c875c7",
       "type": "word",
       "value": "волосся",
       "textRange": [
        1157,
        1164
       ],
       "concept": "SYNTAX"
      }
     ],
     "value": " намащую ним волосся",
     "concept": "SYNTAX"
    },
    {
     "id": "3a61e67a-35df-447c-9f1a-e6cb9dd837b6",
     "type": "punctuation",
     "value": ",",
     "textRange": [
      1164,
      1165
     ],
     "concept": "SYNTAX"
    },
    {
     "id": "5ea2f7d8-6901-4eb2-8098-f6735f7a924b",
     "type": "subSentence",
     "childs": [
      {
       "id": "55e9cf76-2e8b-4dde-ac94-5e42096ad8d6",
       "type": "whitespace",
       "value": " ",
       "textRange": [
        1165,
        1166
       ],
       "concept": "SYNTAX"
      },
      {
       "id": "28be1a8e-f490-4fdd-a362-03a0fdc5d6a6",
       "type": "word",
       "value": "сідаю",
       "textRange": [
        1166,
        1171
       ],
       "concept": "SYNTAX"
      },
      {
       "id": "c9abf103-9754-47d7-bcc9-906a125d4319",
       "type": "whitespace",
       "value": " ",
       "textRange": [
        1171,
        1172
       ],
       "concept": "SYNTAX"
      },
      {
       "id": "859c7ca6-8465-4b91-9e53-d552f2f4c2c7",
       "type": "word",
       "value": "на",
       "textRange": [
        1172,
        1174
       ],
       "concept": "SYNTAX"
      },
      {
       "id": "d5c0b380-5253-4303-9c41-b7683fe328c8",
       "type": "whitespace",
       "value": " ",
       "textRange": [
        1174,
        1175
       ],
       "concept": "SYNTAX"
      },
      {
       "id": "c22ad14a-6a9e-4b96-870e-7a939310abbf",
       "type": "word",
       "value": "сонце",
       "textRange": [
        1175,
        1180
       ],
       "concept": "SYNTAX"
      },
      {
       "id": "77a18ed8-6148-4cd1-9bd8-c18322054aa5",
       "type": "whitespace",
       "value": " ",
       "textRange": [
        1180,
        1181
       ],
       "concept": "SYNTAX"
      },
      {
       "id": "9c2a75b2-4a1a-4c9e-a312-bf6c84a44f4b",
       "type": "word",
       "value": "і",
       "textRange": [
        1181,
        1182
       ],
       "concept": "SYNTAX"
      },
      {
       "id": "aa27d9c0-22dc-447e-81a0-ffa1dfc74b35",
       "type": "whitespace",
       "value": " ",
       "textRange": [
        1182,
        1183
       ],
       "concept": "SYNTAX"
      },
      {
       "id": "fe5aa45a-bb2e-4c02-bc78-2629a1d24695",
       "type": "word",
       "value": "тримаю",
       "textRange": [
        1183,
        1189
       ],
       "concept": "SYNTAX"
      },
      {
       "id": "99663c2d-a77f-41dc-916b-378304bae90c",
       "type": "whitespace",
       "value": " ",
       "textRange": [
        1189,
        1190
       ],
       "concept": "SYNTAX"
      },
      {
       "id": "7e04cf54-db1f-4c34-999f-fa48516c4abe",
       "type": "word",
       "value": "довго",
       "textRange": [
        1190,
        1195
       ],
       "concept": "SYNTAX"
      }
     ],
     "value": " сідаю на сонце і тримаю довго",
     "concept": "SYNTAX"
    },
    {
     "id": "c634115d-314a-4bd1-8abb-7854e463885e",
     "type": "punctuation",
     "value": ",",
     "textRange": [
      1195,
      1196
     ],
     "concept": "SYNTAX"
    },
    {
     "id": "74abb5db-85a6-4811-851b-da17b4014c85",
     "type": "subSentence",
     "childs": [
      {
       "id": "9674364d-dcd8-40dc-84eb-9fa948408089",
       "type": "whitespace",
       "value": " ",
       "textRange": [
        1196,
        1197
       ],
       "concept": "SYNTAX"
      },
      {
       "id": "0770cd63-b7c5-4cc6-a149-8e180775d8d6",
       "type": "word",
       "value": "щоб",
       "textRange": [
        1197,
        1200
       ],
       "concept": "SYNTAX"
      },
      {
       "id": "74f8bb05-5b77-42ad-93d4-a20d0e6e0973",
       "type": "whitespace",
       "value": " ",
       "textRange": [
        1200,
        1201
       ],
       "concept": "SYNTAX"
      },
      {
       "id": "7f755a8c-e3d6-467e-8510-18e92e624ee1",
       "type": "word",
       "value": "ввійшов",
       "textRange": [
        1201,
        1208
       ],
       "concept": "SYNTAX"
      },
      {
       "id": "2dca6512-3926-45ce-97c9-16a8e2bbf6ab",
       "type": "whitespace",
       "value": " ",
       "textRange": [
        1208,
        1209
       ],
       "concept": "SYNTAX"
      },
      {
       "id": "24dad57a-a30d-4acf-b211-888c4ba2f7fd",
       "type": "word",
       "value": "у",
       "textRange": [
        1209,
        1210
       ],
       "concept": "SYNTAX"
      },
      {
       "id": "4fe2d0b9-3171-4fce-a4e7-5dfe3916f488",
       "type": "whitespace",
       "value": " ",
       "textRange": [
        1210,
        1211
       ],
       "concept": "SYNTAX"
      },
      {
       "id": "91a25b4e-47ed-44ea-9f7b-2e50129d4b30",
       "type": "word",
       "value": "голову",
       "textRange": [
        1211,
        1217
       ],
       "concept": "SYNTAX"
      }
     ],
     "value": " щоб ввійшов у голову",
     "concept": "SYNTAX"
    },
    {
     "id": "7a1da22b-2d1e-46e6-9ed5-c06ab291497b",
     "type": "punctuation",
     "value": ".",
     "textRange": [
      1217,
      1218
     ],
     "concept": "SYNTAX"
    }
   ],
   "value": " Я беру мед, намащую ним волосся, сідаю на сонце і тримаю довго, щоб ввійшов у голову",
   "concept": "SYNTAX"
  },
  {
   "id": "d0e69124-2095-4f25-8bc5-336ade278f63",
   "type": "sentence",
   "childs": [
    {
     "id": "f1f50711-4fbf-4cd8-9da0-758d25bd0b4e",
     "type": "subSentence",
     "childs": [
      {
       "id": "71e8fc6c-14f4-410c-a86f-5ba39c38c291",
       "type": "whitespace",
       "value": " ",
       "textRange": [
        1218,
        1219
       ],
       "concept": "SYNTAX"
      },
      {
       "id": "8f5256c8-34b9-414d-bcf8-b4291db90f76",
       "type": "word",
       "value": "А",
       "textRange": [
        1219,
        1220
       ],
       "concept": "SYNTAX"
      },
      {
       "id": "b301302e-0758-451c-aac2-660659da8d5a",
       "type": "whitespace",
       "value": " ",
       "textRange": [
        1220,
        1221
       ],
       "concept": "SYNTAX"
      },
      {
       "id": "a1897c5b-0f18-4bce-ba46-9bcf7a7d9f3e",
       "type": "word",
       "value": "щодо",
       "textRange": [
        1221,
        1225
       ],
       "concept": "SYNTAX"
      },
      {
       "id": "03aab90a-7f84-4ad9-bd9d-652808857d44",
       "type": "whitespace",
       "value": " ",
       "textRange": [
        1225,
        1226
       ],
       "concept": "SYNTAX"
      },
      {
       "id": "dbe7c5f0-343d-4cc2-9796-ec0480e2b306",
       "type": "word",
       "value": "співу",
       "textRange": [
        1226,
        1231
       ],
       "concept": "SYNTAX"
      }
     ],
     "value": " А щодо співу",
     "concept": "SYNTAX"
    },
    {
     "id": "e4c0ffa9-e5cb-412d-ab69-8af5339d547a",
     "type": "punctuation",
     "value": ",",
     "textRange": [
      1231,
      1232
     ],
     "concept": "SYNTAX"
    },
    {
     "id": "a9dd9ee9-3e12-49b7-8c34-aa983ad56a92",
     "type": "subSentence",
     "childs": [
      {
       "id": "6dd46129-e8e1-4acf-81ba-a7630a6a3f8d",
       "type": "whitespace",
       "value": " ",
       "textRange": [
        1232,
        1233
       ],
       "concept": "SYNTAX"
      },
      {
       "id": "0348562a-a9de-4344-af96-bf8f954b8083",
       "type": "word",
       "value": "то",
       "textRange": [
        1233,
        1235
       ],
       "concept": "SYNTAX"
      },
      {
       "id": "e458d1c3-cae7-461e-8acf-f0d5ee8076df",
       "type": "whitespace",
       "value": " ",
       "textRange": [
        1235,
        1236
       ],
       "concept": "SYNTAX"
      },
      {
       "id": "b65f189f-a1de-4cc0-997e-6961f7a58ea7",
       "type": "word",
       "value": "я",
       "textRange": [
        1236,
        1237
       ],
       "concept": "SYNTAX"
      },
      {
       "id": "568168e5-bd54-4443-b86e-ed9b88be8852",
       "type": "whitespace",
       "value": " ",
       "textRange": [
        1237,
        1238
       ],
       "concept": "SYNTAX"
      },
      {
       "id": "495e9f6a-c4fe-4d83-9c21-e4a041cf36e3",
       "type": "word",
       "value": "беру",
       "textRange": [
        1238,
        1242
       ],
       "concept": "SYNTAX"
      },
      {
       "id": "ff9670c8-accb-443e-93cc-1f8eaffe4fc4",
       "type": "whitespace",
       "value": " ",
       "textRange": [
        1242,
        1243
       ],
       "concept": "SYNTAX"
      },
      {
       "id": "b0801d7e-8eec-4162-8cce-aff1a7aad513",
       "type": "word",
       "value": "півсклянки",
       "textRange": [
        1243,
        1253
       ],
       "concept": "SYNTAX"
      },
      {
       "id": "3830cca6-d408-495c-b581-d386d60efd9a",
       "type": "whitespace",
       "value": " ",
       "textRange": [
        1253,
        1254
       ],
       "concept": "SYNTAX"
      },
      {
       "id": "05a42282-8d08-4fad-aed7-2026e6f204e9",
       "type": "word",
       "value": "олії",
       "textRange": [
        1254,
        1258
       ],
       "concept": "SYNTAX"
      },
      {
       "id": "0a1613de-7414-46a2-979b-5aef66424a21",
       "type": "whitespace",
       "value": " ",
       "textRange": [
        1258,
        1259
       ],
       "concept": "SYNTAX"
      },
      {
       "id": "509f5108-3085-4f79-b10d-8b3dd5af1b8d",
       "type": "word",
       "value": "і",
       "textRange": [
        1259,
        1260
       ],
       "concept": "SYNTAX"
      },
      {
       "id": "fbc33527-2000-4fcf-a67b-a05ce31b6847",
       "type": "whitespace",
       "value": " ",
       "textRange": [
        1260,
        1261
       ],
       "concept": "SYNTAX"
      },
      {
       "id": "a545b45c-973d-4d00-9856-8dda81ee286d",
       "type": "word",
       "value": "випиваю",
       "textRange": [
        1261,
        1268
       ],
       "concept": "SYNTAX"
      }
     ],
     "value": " то я беру півсклянки олії і випиваю",
     "concept": "SYNTAX"
    },
    {
     "id": "4c4eece0-a52c-4b1e-9e6c-67753691702c",
     "type": "punctuation",
     "value": ",",
     "textRange": [
      1268,
      1269
     ],
     "concept": "SYNTAX"
    },
    {
     "id": "d38c7e78-ca2a-4716-a2b6-24359e23c276",
     "type": "subSentence",
     "childs": [
      {
       "id": "31741571-0a13-4bd0-8f6d-ade730af2a8e",
       "type": "whitespace",
       "value": " ",
       "textRange": [
        1269,
        1270
       ],
       "concept": "SYNTAX"
      },
      {
       "id": "91ca1575-587d-429f-9ac1-fac5d289a62a",
       "type": "word",
       "value": "щоб",
       "textRange": [
        1270,
        1273
       ],
       "concept": "SYNTAX"
      },
      {
       "id": "f1906fcd-2b5f-48e9-adb1-1892175feb78",
       "type": "whitespace",
       "value": " ",
       "textRange": [
        1273,
        1274
       ],
       "concept": "SYNTAX"
      },
      {
       "id": "018eb619-0be6-454b-82a9-2d6fc6456fc9",
       "type": "word",
       "value": "добре",
       "textRange": [
        1274,
        1279
       ],
       "concept": "SYNTAX"
      },
      {
       "id": "f0b37e3f-5bcf-42f2-a267-f8a2b09e79f6",
       "type": "whitespace",
       "value": " ",
       "textRange": [
        1279,
        1280
       ],
       "concept": "SYNTAX"
      },
      {
       "id": "145bd453-1714-4fc0-9045-a5511c1d0d49",
       "type": "word",
       "value": "змастити",
       "textRange": [
        1280,
        1288
       ],
       "concept": "SYNTAX"
      },
      {
       "id": "3ba4f3ed-2d75-44fd-b337-9fffa6c7091b",
       "type": "whitespace",
       "value": " ",
       "textRange": [
        1288,
        1289
       ],
       "concept": "SYNTAX"
      },
      {
       "id": "bfcb258c-6f81-4db1-85cf-0b85072f1305",
       "type": "word",
       "value": "горло",
       "textRange": [
        1289,
        1294
       ],
       "concept": "SYNTAX"
      }
     ],
     "value": " щоб добре змастити горло",
     "concept": "SYNTAX"
    },
    {
     "id": "63c966c6-ec18-4643-ba18-d6b06f4e815f",
     "type": "punctuation",
     "value": ",",
     "textRange": [
      1294,
      1295
     ],
     "concept": "SYNTAX"
    },
    {
     "id": "e306341a-f4c5-4ff6-a861-395ce67f6764",
     "type": "subSentence",
     "childs": [
      {
       "id": "191809f1-be86-4326-81e7-f4365b4e3fce",
       "type": "whitespace",
       "value": " ",
       "textRange": [
        1295,
        1296
       ],
       "concept": "SYNTAX"
      },
      {
       "id": "81a1fd3c-2694-48be-9a7f-2ae06c974442",
       "type": "word",
       "value": "-",
       "textRange": [
        1296,
        1297
       ],
       "concept": "SYNTAX"
      },
      {
       "id": "bf28b99e-32db-43e9-b492-a7fe32977ac1",
       "type": "whitespace",
       "value": " ",
       "textRange": [
        1297,
        1298
       ],
       "concept": "SYNTAX"
      },
      {
       "id": "4e4748d1-a8f8-4540-918a-2d69411f2ab7",
       "type": "word",
       "value": "ото",
       "textRange": [
        1298,
        1301
       ],
       "concept": "SYNTAX"
      },
      {
       "id": "3a919508-0905-4a93-9480-a11c48638187",
       "type": "whitespace",
       "value": " ",
       "textRange": [
        1301,
        1302
       ],
       "concept": "SYNTAX"
      },
      {
       "id": "de2b822f-acb8-47a9-b84e-5a7a39201945",
       "type": "word",
       "value": "співається",
       "textRange": [
        1302,
        1312
       ],
       "concept": "SYNTAX"
      },
      {
       "id": "4f7383e7-9c0a-477d-835d-e12d6af7dc71",
       "type": "whitespace",
       "value": " ",
       "textRange": [
        1312,
        1313
       ],
       "concept": "SYNTAX"
      },
      {
       "id": "860c2131-1801-4691-b4d2-c26526662fe2",
       "type": "word",
       "value": "потім",
       "textRange": [
        1313,
        1318
       ],
       "concept": "SYNTAX"
      }
     ],
     "value": " - ото співається потім",
     "concept": "SYNTAX"
    },
    {
     "id": "22619b42-d27a-44f9-a647-2f1cc65d3fed",
     "type": "punctuation",
     "value": "!",
     "textRange": [
      1318,
      1319
     ],
     "concept": "SYNTAX"
    },
    {
     "id": "aade158a-4102-41cd-9892-90bdb31bf96c",
     "type": "punctuation",
     "value": "\n",
     "textRange": [
      1319,
      1320
     ],
     "concept": "SYNTAX"
    }
   ],
   "value": " А щодо співу, то я беру півсклянки олії і випиваю, щоб добре змастити горло, - ото співається потім!",
   "concept": "SYNTAX"
  }
 ],
 "value": "- Я тобі скажу, але ти нікому не переповідай, бо можна зле напророчити Я беру мед, намащую ним волосся, сідаю на сонце і тримаю довго, щоб ввійшов у голову А щодо співу, то я беру півсклянки олії і випиваю, щоб добре змастити горло, - ото співається потім!",
 "concept": "SYNTAX"
}