{
 "id": "d6cbc489-d95e-4981-9bea-f9cb4cfffe18",
 "type": "paragraph",
 "childs": [
  {
   "id": "e9f70f8a-b344-4846-9d5f-30c57e45e4c7",
   "type": "sentence",
   "childs": [
    {
     "id": "47a8e9dd-0a43-4861-9307-03026c8c585c",
     "type": "subSentence",
     "childs": [
      {
       "id": "da75dd10-cb2f-4d8a-8e8e-e66fd086f20e",
       "type": "word",
       "value": "Воно",
       "textRange": [
        353,
        357
       ],
       "concept": "SYNTAX"
      },
      {
       "id": "74b4b537-aef3-417a-9d09-ffb645b544dd",
       "type": "whitespace",
       "value": " ",
       "textRange": [
        357,
        358
       ],
       "concept": "SYNTAX"
      },
      {
       "id": "dce46c47-fb06-437a-b16c-19f56ab57111",
       "type": "word",
       "value": "мало",
       "textRange": [
        358,
        362
       ],
       "concept": "SYNTAX"
      },
      {
       "id": "bcf20348-f7d3-4f54-9e58-c14477c7748d",
       "type": "whitespace",
       "value": " ",
       "textRange": [
        362,
        363
       ],
       "concept": "SYNTAX"
      },
      {
       "id": "fb35f43e-4ca2-49c4-9e58-1b4d9ee91957",
       "type": "word",
       "value": "хутро",
       "textRange": [
        363,
        368
       ],
       "concept": "SYNTAX"
      },
      {
       "id": "debddd54-3688-47a7-be3a-1937a7625ae6",
       "type": "whitespace",
       "value": " ",
       "textRange": [
        368,
        369
       ],
       "concept": "SYNTAX"
      },
      {
       "id": "19b2d44e-5380-4581-9b2c-c666f15c5958",
       "type": "word",
       "value": "кольору",
       "textRange": [
        369,
        376
       ],
       "concept": "SYNTAX"
      },
      {
       "id": "b3d7c2f7-66e2-4e2a-b720-64eebc325d67",
       "type": "whitespace",
       "value": " ",
       "textRange": [
        376,
        377
       ],
       "concept": "SYNTAX"
      },
      {
       "id": "7777526d-fd17-4a01-acf4-39f078825088",
       "type": "word",
       "value": "неба",
       "textRange": [
        377,
        381
       ],
       "concept": "SYNTAX"
      }
     ],
     "value": "Воно мало хутро кольору неба",
     "concept": "SYNTAX"
    },
    {
     "id": "ad569293-6e00-46cd-8670-8b057483806c",
     "type": "punctuation",
     "value": ".",
     "textRange": [
      381,
      382
     ],
     "concept": "SYNTAX"
    }
   ],
   "value": "Воно мало хутро кольору неба",
   "concept": "SYNTAX"
  },
  {
   "id": "97f8f4e4-e3a5-4b2f-8176-3f06ed84c071",
   "type": "sentence",
   "childs": [
    {
     "id": "119eab5a-2479-4fe3-9dcd-5bf1f5c2fa00",
     "type": "subSentence",
     "childs": [
      {
       "id": "a7d808aa-ae6f-449e-aa3c-047969682eb2",
       "type": "whitespace",
       "value": " ",
       "textRange": [
        382,
        383
       ],
       "concept": "SYNTAX"
      },
      {
       "id": "b90764dc-4998-43cb-ba44-18b8f4840e6b",
       "type": "word",
       "value": "А",
       "textRange": [
        383,
        384
       ],
       "concept": "SYNTAX"
      },
      {
       "id": "c7ac6b08-2125-4aae-ad0b-516ea5f9d7c8",
       "type": "whitespace",
       "value": " ",
       "textRange": [
        384,
        385
       ],
       "concept": "SYNTAX"
      },
      {
       "id": "3178edc6-a396-48ed-9da7-6eba640b2b7c",
       "type": "word",
       "value": "хіба",
       "textRange": [
        385,
        389
       ],
       "concept": "SYNTAX"
      },
      {
       "id": "98512850-a6cb-4528-a86c-804e1bff69b2",
       "type": "whitespace",
       "value": " ",
       "textRange": [
        389,
        390
       ],
       "concept": "SYNTAX"
      },
      {
       "id": "393e403b-2ac0-4ff7-8e1f-2658861184d2",
       "type": "word",
       "value": "бачив",
       "textRange": [
        390,
        395
       ],
       "concept": "SYNTAX"
      },
      {
       "id": "ded2d76e-71d7-4379-ba0d-e6a4c8043254",
       "type": "whitespace",
       "value": " ",
       "textRange": [
        395,
        396
       ],
       "concept": "SYNTAX"
      },
      {
       "id": "cbc0adf5-b0f5-4c90-9fae-5df425cb64dd",
       "type": "word",
       "value": "хтось",
       "textRange": [
        396,
        401
       ],
       "concept": "SYNTAX"
      },
      {
       "id": "e3ed9252-cd0d-48fc-b515-a8295bcf93d4",
       "type": "whitespace",
       "value": " ",
       "textRange": [
        401,
        402
       ],
       "concept": "SYNTAX"
      },
      {
       "id": "ee49421c-6a7f-43b3-9cac-0a1b8645a94b",
       "type": "word",
       "value": "колись",
       "textRange": [
        402,
        408
       ],
       "concept": "SYNTAX"
      },
      {
       "id": "4819f05b-3a14-491d-8f64-2b9069878dd3",
       "type": "whitespace",
       "value": " ",
       "textRange": [
        408,
        409
       ],
       "concept": "SYNTAX"
      },
      {
       "id": "ed034af7-6c58-4844-ba78-e3b9938d979a",
       "type": "word",
       "value": "киць",
       "textRange": [
        409,
        413
       ],
       "concept": "SYNTAX"
      },
      {
       "id": "9edf950f-0d00-4928-a36d-7dc0cb32e464",
       "type": "whitespace",
       "value": " ",
       "textRange": [
        413,
        414
       ],
       "concept": "SYNTAX"
      },
      {
       "id": "6010a8a8-83cb-4b3a-9190-46f0c8872eef",
       "type": "word",
       "value": "із",
       "textRange": [
        414,
        416
       ],
       "concept": "SYNTAX"
      },
      {
       "id": "040bfac5-41eb-4183-b58e-0eccacd016ec",
       "type": "whitespace",
       "value": " ",
       "textRange": [
        416,
        417
       ],
       "concept": "SYNTAX"
      },
      {
       "id": "2d9704c6-ad36-4b27-b083-8d00e7069ca4",
       "type": "word",
       "value": "хутром",
       "textRange": [
        417,
        423
       ],
       "concept": "SYNTAX"
      },
      {
       "id": "a6ed1898-b163-4dfc-b269-4c4057bbfde4",
       "type": "whitespace",
       "value": " ",
       "textRange": [
        423,
        424
       ],
       "concept": "SYNTAX"
      },
      {
       "id": "d59ca711-4562-4e83-964a-420c72125488",
       "type": "word",
       "value": "якогось",
       "textRange": [
        424,
        431
       ],
       "concept": "SYNTAX"
      },
      {
       "id": "a555a5ac-0c0a-4455-bbfa-e9e1094f8e9e",
       "type": "whitespace",
       "value": " ",
       "textRange": [
        431,
        432
       ],
       "concept": "SYNTAX"
      },
      {
       "id": "d7bb89e6-156c-483d-b5e8-2f069f114f67",
       "type": "word",
       "value": "іншого",
       "textRange": [
        432,
        438
       ],
       "concept": "SYNTAX"
      },
      {
       "id": "87f5a5d0-aa22-431b-a61f-b261db27d881",
       "type": "whitespace",
       "value": " ",
       "textRange": [
        438,
        439
       ],
       "concept": "SYNTAX"
      },
      {
       "id": "2ebb2bd5-f20f-4ba0-b248-ca0f49231baa",
       "type": "word",
       "value": "кольору",
       "textRange": [
        439,
        446
       ],
       "concept": "SYNTAX"
      },
      {
       "id": "312f5dae-7007-445e-a3db-e52774762147",
       "type": "whitespace",
       "value": "...",
       "textRange": [
        446,
        449
       ],
       "concept": "SYNTAX"
      }
     ],
     "value": " А хіба бачив хтось колись киць із хутром якогось іншого кольору...",
     "concept": "SYNTAX"
    },
    {
     "id": "78234dd4-bd0c-4589-bd9d-bcdb9e39d059",
     "type": "punctuation",
     "value": "\n",
     "textRange": [
      449,
      450
     ],
     "concept": "SYNTAX"
    }
   ],
   "value": " А хіба бачив хтось колись киць із хутром якогось іншого кольору...",
   "concept": "SYNTAX"
  }
 ],
 "value": "Воно мало хутро кольору неба А хіба бачив хтось колись киць із хутром якогось іншого кольору...",
 "concept": "SYNTAX"
}